discord_emoji_ranking/__init__.py
discord_emoji_ranking/module.py
discord_emoji_ranking-0.1.1.dist-info/METADATA
discord_emoji_ranking-0.1.1.dist-info/WHEEL
discord_emoji_ranking-0.1.1.dist-info/top_level.txt
discord_emoji_ranking-0.1.1.dist-info/RECORD
