Metadata-Version: 2.1
Name: discord-emoji-ranking
Version: 0.1.1
Summary: Discord BOT to provide emoji usage ranking
Home-page: https://github.com/jukey17/discord-emoji-ranking
Author: jukey17
License: MIT
Keywords: discord,discord.py
Classifier: Programming Language :: Python :: 3
Classifier: License :: OSI Approved :: MIT License
Requires-Dist: discord (~=1.7.3)
Requires-Dist: discord-ext-commands-coghelper
